spykes/__init__.py
spykes/parsing.py
spykes/secret.py
spykes/spk.py
spykes/store.py
spykes/store_manager.py
test/__init__.py
test/test_main.py
test/test_parsing.py
test/test_secret.py
test/test_store.py
spykeys-0.1.6.dist-info/LICENSE
spykeys-0.1.6.dist-info/METADATA
spykeys-0.1.6.dist-info/WHEEL
spykeys-0.1.6.dist-info/entry_points.txt
spykeys-0.1.6.dist-info/top_level.txt
spykeys-0.1.6.dist-info/RECORD
