Metadata-Version: 2.1
Name: spykeys
Version: 0.1.6
Summary: This is the SPyKeS package. It provides simple key storage capabilities.
Home-page: https://github.com/Pythocrates/SPyKeS
Author: Pythocrates
Author-email: 23015037+Pythocrates@users.noreply.github.com
License: UNKNOWN
Platform: UNKNOWN
Classifier: Development Status :: 3 - Alpha
Classifier: Environment :: Console
Classifier: Programming Language :: Python :: 3.6
Classifier: Programming Language :: Python :: 3.7
Classifier: Programming Language :: Python :: 3.8
Classifier: License :: OSI Approved :: MIT License
Classifier: Operating System :: POSIX :: Linux
Requires-Dist: GitPython (>=3.1.7)
Requires-Dist: python-gnupg (>=0.4.6)
